Workbook

Sheet Assumption
D4: Inflation Rate | E4: 0.02
D5: Average unit selling price (HKD) | E5: 500000
D6: Average maintenance price (HKD) | E6: 2000
D7: Gross profit margin (%) for Sales | E7: 0.09
D8: Gross profit margin (%) for Aftersales | E8: 0.35
D9: Target | E9: 12% of market

Sheet Caculation V2 (HK)
B3: EV VAN
C4: 2021 | D4: 2022 | E4: 20223Q1 | F4: 2023 | G4: 2024 | H4: 2025 | I4: 2026 | J4: 2027 | K4: 2028 | L4: 2029 | M4: 2030 | N4: Total
B5: Vehicle sales
B6: Total market - | C6: 1439 | D6: 983 | E6: 287 | F6: 711 | G6: 1014.12 | H6: 263.4 | I6: 386.55 | J6: 436 | K6: 540 | L6: 630 | M6: 720
B7: Unit of car sold | H7: 0 | I7: 10 | J7: =J6*0.08 -> 34.88 | K7: =K6*0.1 -> 54 | L7: =L6*0.12 -> 75.6 | M7: =M6*0.12 -> 86.4
B8: Average unit selling price (HKD) | H8: 500000 | I8: =H8*1.02 -> 510000 | J8: =I8*1.02 -> 520200 | K8: =J8*1.02 -> 530604 | L8: =K8*1.02 -> 541216.08 | M8: =L8*1.02 -> 552040.4
B9: Revenue (HKD) | C9: =C8*C7 -> 0 | D9: =D8*D7 -> 0 | E9: =E8*E7 -> 0 | F9: =F8*F7 -> 0 | G9: =G8*G7 -> 0 | H9: =H8*H7 -> 0 | I9: =I8*I7 -> 5100000 | J9: =J8*J7 -> 18144576 | ... M9: =M8*M7 -> 47696291 | N9: =SUM(C9:M9) -> 1.4050942e+08
B10: Gross profit margin (%) | C10: 0.09 | D10: 0.09 | E10: 0.09 | F10: 0.09 | G10: 0.09 | H10: =Assumption!$E$7 -> 0.09 | I10: =Assumption!$E$7 -> 0.09 | J10: =Assumption!$E$7 -> 0.09 | K10: =Assumption!$E$7 -> 0.09 | L10: =Assumption!$E$7 -> 0.09 | M10: =Assumption!$E$7 -> 0.09
B11: Opex(Showroom)(HKD)
B12: Gross profit (HKD) | C12: =C9*C10 -> 0 | D12: =D9*D10 -> 0 | E12: =E9*E10 -> 0 | F12: =F9*F10 -> 0 | G12: =G9*G10 -> 0 | H12: =H9*H10+H11 -> 0 | I12: =I9*I10+I11 -> 459000 | J12: =J9*J10+J11 -> 1633011.8 | K12: =K9*K10+K11 -> 2578735.4 | L12: =L9*L10+L11 -> 3682434.2 | M12: =M9*M10+M11 -> 4292666.2 | N12: =SUM(C12:M12) -> 12645848
B13: Accumulated Gross profit (HKD) | H13: =H12 -> 0 | I13: =H13+I12 -> 459000 | J13: =I13+J12 -> 2092011.8 | K13: =J13+K12 -> 4670747.3 | L13: =K13+L12 -> 8353181.5 | M13: =L13+M12 -> 12645848
C15: 2021 | D15: 2022 | E15: 20223Q1 | F15: 2023 | G15: 2024 | H15: 2025 | I15: 2026 | J15: 2027 | K15: 2028 | L15: 2029 | M15: 2030 | N15: Total
B16: Workshop sales
B17: Car population (#) | C17: =C7 -> 0 | D17: =D7 -> 0 | E17: =E7 -> 0 | F17: =F7 -> 0 | G17: =G7 -> 0 | H17: =H7 -> 0 | I17: =SUM($H$7:I7) -> 10 | J17: =SUM($H$7:J7) -> 44.88 | K17: =SUM($H$7:K7) -> 98.88 | L17: =SUM($H$7:L7) -> 174.48 | M17: =SUM($H$7:M7) -> 260.88
B18: Average maintenance price (HKD) | H18: 2000 | I18: =H18*1.02 -> 2040 | J18: =I18*1.02 -> 2080.8 | K18: =J18*1.02 -> 2122.416 | L18: =K18*1.02 -> 2164.8643 | M18: =L18*1.02 -> 2208.1616
B19: Revenue (HKD) | H19: =H17*H18 -> 0 | I19: =I17*I18 -> 20400 | J19: =J17*J18 -> 93386.304 | K19: =K17*K18 -> 209864.49 | L19: =L17*L18 -> 377725.53 | M19: =M17*M18 -> 576065.2 | N19: =SUM(C19:M19) -> 1277441.5
B20: Gross profit margin (%) | H20: 0.35 | I20: 0.35 | J20: 0.35 | K20: 0.35 | L20: 0.35 | M20: 0.35
B21: Gross profit (HKD) | C21: =C19*C20 -> 0 | D21: =D19*D20 -> 0 | E21: =E19*E20 -> 0 | F21: =F19*F20 -> 0 | G21: =G19*G20 -> 0 | H21: =H19*H20 -> 0 | I21: =I19*I20 -> 7140 | J21: =J19*J20 -> 32685.206 | ... M21: =M19*M20 -> 201622.82 | N21: =SUM(C21:M21) -> 447104.53
B22: Accumulated Gross profit (HKD) | H22: =H21 -> 0 | I22: =H22+I21 -> 7140 | J22: =I22+J21 -> 39825.206 | K22: =J22+K21 -> 113277.78 | L22: =K22+L21 -> 245481.71 | M22: =L22+M21 -> 447104.53
M23: Total Profit | N23: =N21+N12 -> 13092952
B64: 2034
B65: 38806.805
B66: 55191.606
B67: 93998.411
